wastimate/__init__.py
wastimate/framework.py
wastimate-0.0.5.dist-info/METADATA
wastimate-0.0.5.dist-info/WHEEL
wastimate-0.0.5.dist-info/top_level.txt
wastimate-0.0.5.dist-info/RECORD
