Metadata-Version: 2.1
Name: wastimate
Version: 0.0.5
Summary: General framework for estimating waste quantities in time.
Home-page: UNKNOWN
Author: Hando Tohver
Author-email: <handotohver@gmail.com>
License: UNKNOWN
Keywords: python,radioactive waste,Modeling
Platform: UNKNOWN
Classifier: Development Status :: 3 - Alpha
Classifier: Intended Audience :: Science/Research
Classifier: Programming Language :: Python :: 3
Classifier: Operating System :: Microsoft :: Windows
Classifier: License :: OSI Approved :: MIT License
Requires-Dist: numpy
Requires-Dist: scipy
Requires-Dist: matplotlib
